quati/__init__.py
quati/data/__init__.py
quati/data/df_normalizer.py
quati/google/big_query.py
quati/google/sheets.py
quati/logger/__init__.py
quati/messenger/__init__.py
quati/messenger/gmail.py
quati/scrapping/__init__.py
quati/scrapping/selenium.py
quati/system/__init__.py
quati/system/linux_utils.py
quati-1.2.1.dist-info/licenses/AUTHORS.md
quati-1.2.1.dist-info/licenses/LICENSE
quati-1.2.1.dist-info/METADATA
quati-1.2.1.dist-info/WHEEL
quati-1.2.1.dist-info/top_level.txt
quati-1.2.1.dist-info/RECORD
