Metadata-Version: 2.4
Name: quati
Version: 1.2.1
Summary: Dynamic data eng. functions to accelerate development and coding
Author: lucaslealll
License: MIT
Project-URL: Homepage, https://pypi.org/project/quati
Project-URL: Documentation, https://github.com/quati-dev/quati/blob/main/doc/DOCUMENTATION.md
Project-URL: Repository, https://github.com/quati-dev/quati
Keywords: quick,actions,toolkit,functions
Classifier: Development Status :: 4 - Beta
Classifier: Intended Audience :: Developers
Classifier: License :: OSI Approved :: MIT License
Classifier: Programming Language :: Python :: 3.10
Classifier: Topic :: Software Development :: Libraries
Requires-Python: >=3.10
License-File: LICENSE
License-File: AUTHORS.md
Requires-Dist: google-cloud-bigquery==2.34.4
Requires-Dist: google-cloud-bigquery-storage==2.27.0
Requires-Dist: gspread==5.5.0
Requires-Dist: oauthlib==3.2.2
Requires-Dist: pandas==1.3.4
Requires-Dist: pandas-gbq==0.14.1
Requires-Dist: requests==2.32.3
Requires-Dist: selenium==4.7.2
Requires-Dist: tqdm==4.67.1
Dynamic: license-file
